Metadata-Version: 2.1
Name: mathutilities
Version: 0.1.0
Summary: To perform various mathematical calculations
Author: Gopi Krishna Manne
Author-email: iqagopi@gmail.com
Classifier: Programming Language :: Python :: 3
Classifier: License :: OSI Approved :: MIT License
Classifier: Operating System :: OS Independent
Requires-Python: >=3.6
License-File: LICENSE.txt
